frame_story/__init__.py
frame_story/video_describer.py
framestory-2025.4.231619.dist-info/licenses/LICENSE
tests/__init__.py
tests/test_video_describer.py
framestory-2025.4.231619.dist-info/METADATA
framestory-2025.4.231619.dist-info/WHEEL
framestory-2025.4.231619.dist-info/top_level.txt
framestory-2025.4.231619.dist-info/RECORD
