Metadata-Version: 2.4
Name: FrameStory
Version: 2025.4.231619
Summary: A Python package for creating video descriptions by analyzing and extracting significant frames.
Home-page: https://github.com/chigwell/FrameStory
Author: Eugene Evstafev
Author-email: chigwel@gmail.com
Classifier: License :: OSI Approved :: MIT License
Classifier: Development Status :: 3 - Alpha
Classifier: Intended Audience :: Developers
Classifier: Topic :: Multimedia :: Video
Classifier: Programming Language :: Python :: 3
Classifier: Programming Language :: Python :: 3.6
Classifier: Programming Language :: Python :: 3.7
Classifier: Programming Language :: Python :: 3.8
Classifier: Programming Language :: Python :: 3.9
Classifier: Programming Language :: Python :: 3.10
Classifier: Programming Language :: Python :: 3.11
Classifier: Operating System :: OS Independent
Requires-Python: >=3.6
License-File: LICENSE
Requires-Dist: requests<3,>=2.25
Requires-Dist: opencv-python<5,>=4.0
Requires-Dist: numpy<2,>=1.19
Requires-Dist: Pillow<9,>=8.0
Requires-Dist: transformers<5,>=4.0
Requires-Dist: tqdm<5,>=4.0
Dynamic: author
Dynamic: author-email
Dynamic: classifier
Dynamic: description
Dynamic: description-content-type
Dynamic: home-page
Dynamic: license-file
Dynamic: requires-dist
Dynamic: requires-python
Dynamic: summary
